{
  "displayName": "Open Spaces",
  "description": "Connect to GitHub Codespaces from Code-OSS/VS Codium using GitHub CLI and open-remote-ssh",
  "viewsContainers.openSpaces.title": "GitHub Codespaces",
  "views.codespaceTree.name": "Codespaces",
  "command.connect.title": "Connect to Codespace",
  "command.start.title": "Start Codespace",
  "command.stop.title": "Stop Codespace",
  "command.refresh.title": "Refresh Codespaces",
  "command.openAuthTerminal.title": "Authenticate with GitHub CLI",
  "command.rebuild.title": "Rebuild Codespace",
  "command.rebuildFull.title": "Rebuild Codespace (Full)",
  "command.disconnect.title": "Disconnect from Codespace",
  "command.delete.title": "Delete Codespace",
  "command.create.title": "Create Codespace",
  "command.openSshTerminal.title": "Open SSH Terminal",
  "command.addCodespaceScope.title": "Add Codespace Scope",
  "command.statusBarActions.title": "Codespace Status Bar Actions",
  "command.filterByText.title": "Filter Codespaces by Text",
  "command.filterByState.title": "Filter Codespaces by State",
  "command.clearFilters.title": "Clear Codespace Filters",
  "command.bulkStop.title": "Stop Selected Codespaces",
  "command.bulkDelete.title": "Delete Selected Codespaces",
  "command.manageTemplates.title": "Manage Codespace Templates",
  "command.previewDevcontainer.title": "Preview Devcontainer",
  "config.sshConfigPath.description": "Path to the SSH config file (default: ~/.ssh/config)",
  "config.pollingInterval.description": "Polling interval in milliseconds for transitional state updates (default: 5000)",
  "config.backgroundRefreshInterval.description": "Background refresh interval in milliseconds when the tree view is visible (default: 60000)",
  "config.sshProbeRetries.description": "Number of SSH readiness probe retries before connecting (default: 3)",
  "config.sshProbeDelay.description": "Delay in milliseconds between SSH readiness probe attempts (default: 3000)",
  "config.defaultMachineType.description": "Default machine type to pre-select when creating codespaces (e.g. 'basicLinux32gb')",
  "config.defaultIdleTimeout.description": "Default idle timeout in minutes for new codespaces (0 = use GitHub default)",
  "config.staleThresholdDays.description": "Number of days after which an unused codespace is considered stale (default: 14)",
  "config.detectStaleCodespaces.description": "Show a notification on startup when stale codespaces are detected (default: true)",
  "config.connectionCheckInterval.description": "Interval in seconds between connection health checks when inside a codespace (default: 30)",
  "config.templates.description": "Saved codespace creation templates"
}
